r5py/__init__.py
r5py/__main__.py
r5py/r5/__init__.py
r5py/r5/access_leg.py
r5py/r5/base_travel_time_matrix.py
r5py/r5/detailed_itineraries.py
r5py/r5/direct_leg.py
r5py/r5/egress_leg.py
r5py/r5/elevation_cost_function.py
r5py/r5/elevation_model.py
r5py/r5/file_storage.py
r5py/r5/isochrones.py
r5py/r5/regional_task.py
r5py/r5/scenario.py
r5py/r5/street_layer.py
r5py/r5/street_segment.py
r5py/r5/transfer_leg.py
r5py/r5/transit_layer.py
r5py/r5/transit_leg.py
r5py/r5/transport_mode.py
r5py/r5/transport_network.py
r5py/r5/travel_time_matrix.py
r5py/r5/trip.py
r5py/r5/trip_leg.py
r5py/r5/trip_planner.py
r5py/util/__init__.py
r5py/util/camel_to_snake_case.py
r5py/util/classpath.py
r5py/util/config.py
r5py/util/contains_gtfs_data.py
r5py/util/data_validation.py
r5py/util/environment.py
r5py/util/exceptions.py
r5py/util/file_digest.py
r5py/util/good_enough_equidistant_crs.py
r5py/util/jvm.py
r5py/util/memory_footprint.py
r5py/util/parse_int_date.py
r5py/util/sample_data_set.py
r5py/util/snake_to_camel_case.py
r5py/util/spatially_clustered_geodataframe.py
r5py/util/validating_requests_session.py
r5py/util/warnings.py
r5py/util/working_copy.py
r5py-1.0.7.dist-info/licenses/LICENSE
r5py-1.0.7.dist-info/METADATA
r5py-1.0.7.dist-info/WHEEL
r5py-1.0.7.dist-info/top_level.txt
r5py-1.0.7.dist-info/RECORD
