Metadata-Version: 2.4
Name: r5py
Version: 1.0.7
Summary: Python wrapper for the R5 routing analysis engine
Author: Christoph Fink, Willem Klumpenhouwer, Marcus Sairava, Rafael Pereira, Henrikki Tenkanen
License: GPL-3.0-or-later or MIT
Project-URL: Documentation, https://r5py.readthedocs.org/
Project-URL: Repository, https://github.com/r5py/r5py.git
Project-URL: Change log, https://github.com/r5py/r5py/blob/main/CHANGELOG.md
Project-URL: Bug tracker, https://github.com/r5py/r5py/issues
Keywords: accessibility,transport,routing,research
Classifier: Programming Language :: Python :: 3
Classifier: License :: OSI Approved :: GNU General Public License v3 (GPLv3)
Classifier: License :: OSI Approved :: MIT License
Classifier: Operating System :: OS Independent
Requires-Python: >=3.10
License-File: LICENSE
Requires-Dist: ConfigArgParse
Requires-Dist: filelock
Requires-Dist: geohexgrid
Requires-Dist: geopandas<1.1.0
Requires-Dist: joblib
Requires-Dist: jpype1
Requires-Dist: numpy
Requires-Dist: pandas>=2.1.0
Requires-Dist: psutil
Requires-Dist: pyproj
Requires-Dist: rasterio
Requires-Dist: requests
Requires-Dist: scikit-learn
Requires-Dist: shapely>=2.0
Requires-Dist: simplification
Requires-Dist: typing_extensions; python_version < "3.13"
Provides-Extra: docs
Requires-Dist: contextily; extra == "docs"
Requires-Dist: folium; extra == "docs"
Requires-Dist: GitPython; extra == "docs"
Requires-Dist: h3>=4.0.0b2; extra == "docs"
Requires-Dist: jupyterlab_myst; extra == "docs"
Requires-Dist: mapclassify; extra == "docs"
Requires-Dist: matplotlib; extra == "docs"
Requires-Dist: myst-nb; extra == "docs"
Requires-Dist: nbsphinx; extra == "docs"
Requires-Dist: pybtex-apa7-style; extra == "docs"
Requires-Dist: r5py.sampledata.helsinki>=0.1.1; extra == "docs"
Requires-Dist: r5py.sampledata.sao_paulo>=0.1.1; extra == "docs"
Requires-Dist: shapely; extra == "docs"
Requires-Dist: sphinx; extra == "docs"
Requires-Dist: sphinx-book-theme; extra == "docs"
Requires-Dist: sphinx-design; extra == "docs"
Requires-Dist: sphinxcontrib-bibtex; extra == "docs"
Requires-Dist: sphinxcontrib-images; extra == "docs"
Provides-Extra: tests
Requires-Dist: pyarrow; extra == "tests"
Requires-Dist: pytest; extra == "tests"
Requires-Dist: pytest-cov; extra == "tests"
Requires-Dist: pytest-lazy-fixtures; extra == "tests"
Requires-Dist: r5py.sampledata.helsinki>=1.0.3; extra == "tests"
Requires-Dist: r5py.sampledata.sao_paulo>=0.1.1; extra == "tests"
Requires-Dist: typing-extensions; extra == "tests"
Dynamic: license-file
